{
  "generatedAt": "2026-02-14T09:47:25.614Z",
  "expectedReview": 66,
  "actualReview": 66,
  "missingInReviewCount": 0,
  "missingInReview": [],
  "extraInReviewCount": 0,
  "extraInReview": [],
  "duplicateReviewIdsCount": 0,
  "duplicateReviewIds": [],
  "expectedPublishedAffairs": 8,
  "actualMotions": 8,
  "missingInMotionsCount": 0,
  "missingInMotions": [],
  "reviewDecisionsCount": 698,
  "decisionsUnknownInDbCount": 31,
  "decisionsUnknownLegacyCount": 31,
  "decisionsUnknownCriticalCount": 0,
  "decisionsUnknownInDb": [
    "ch-parliament-business-de:20213835",
    "ch-parliament-business-de:20213405",
    "ch-parliament-business-de:20254809",
    "ch-parliament-business-de:20254812",
    "ch-parliament-business-de:20244465",
    "ch-parliament-business-de:20237858",
    "ch-parliament-business-de:20237657",
    "ch-parliament-business-de:20237608",
    "ch-parliament-business-de:20237131",
    "ch-parliament-business-de:20223728",
    "ch-parliament-business-de:20213829",
    "ch-parliament-business-de:20254380",
    "ch-parliament-business-de:20254010",
    "ch-parliament-business-de:20237580",
    "ch-parliament-business-de:20233411",
    "ch-parliament-business-de:20223299",
    "ch-parliament-business-de:20223187",
    "ch-parliament-business-de:20227004",
    "ch-parliament-business-de:20214435",
    "ch-parliament-business-de:20218161",
    "ch-parliament-business-de:20218163",
    "ch-parliament-business-de:20218162",
    "ch-parliament-business-de:20223633",
    "ch-parliament-business-de:20254788",
    "ch-parliament-business-de:20250078",
    "ch-parliament-business-de:20233515",
    "ch-parliament-business-de:20237115",
    "ch-parliament-business-de:20227807",
    "ch-parliament-business-de:20258205",
    "ch-parliament-business-de:20244696",
    "ch-parliament-business-de:20244695"
  ],
  "decisionsStatusMismatchCount": 0,
  "decisionsStatusMismatch": []
}